flux_bootstrap/__init__.py
flux_bootstrap/api.py
flux_bootstrap/cdn_manager.py
flux_bootstrap/data_structures.py
flux_bootstrap/download_manager.py
flux_bootstrap/main.py
flux_bootstrap/progress_display.py
flux_bootstrap/speed_monitor.py
flux_bootstrap/state_manager.py
flux_bootstrap/worker_processes.py
flux_bootstrap-0.18.1.dist-info/WHEEL
flux_bootstrap-0.18.1.dist-info/entry_points.txt
flux_bootstrap-0.18.1.dist-info/METADATA
flux_bootstrap-0.18.1.dist-info/RECORD
