Metadata-Version: 2.3
Name: flux-bootstrap
Version: 0.18.1
Requires-Dist: aiohttp>=3.13.3
Requires-Dist: aiofiles>=25.1.0
Requires-Dist: pyyaml>=6.0.3
Requires-Dist: setproctitle>=1.3.7
Requires-Dist: click>=8.3.1
Requires-Dist: rich>=13.9.4
Requires-Python: >=3.13
